bpmn2neo/__init__.py
bpmn2neo/cli.py
bpmn2neo/settings.py
bpmn2neo/config/__init__.py
bpmn2neo/config/exceptions.py
bpmn2neo/config/logger.py
bpmn2neo/config/neo4j_repo.py
bpmn2neo/embedder/__init__.py
bpmn2neo/embedder/builder.py
bpmn2neo/embedder/context_writer.py
bpmn2neo/embedder/embedder.py
bpmn2neo/embedder/orchestrator.py
bpmn2neo/embedder/reader.py
bpmn2neo/loader/__init__.py
bpmn2neo/loader/loader.py
bpmn2neo/loader/parser.py
bpmn2neo/utils/__init__.py
bpmn2neo/utils/keyring.py
bpmn2neo-0.2.4.dist-info/licenses/LICENSE
bpmn2neo-0.2.4.dist-info/METADATA
bpmn2neo-0.2.4.dist-info/WHEEL
bpmn2neo-0.2.4.dist-info/entry_points.txt
bpmn2neo-0.2.4.dist-info/top_level.txt
bpmn2neo-0.2.4.dist-info/RECORD
